opendrive2tessng/__init__.py
opendrive2tessng/main.py
opendrive2tessng/opendrive2lanelet/__init__.py
opendrive2tessng/opendrive2lanelet/conversion_lanelet.py
opendrive2tessng/opendrive2lanelet/conversion_lanelet_network.py
opendrive2tessng/opendrive2lanelet/converter.py
opendrive2tessng/opendrive2lanelet/network.py
opendrive2tessng/opendrive2lanelet/utils.py
opendrive2tessng/opendrive2lanelet/io/__init__.py
opendrive2tessng/opendrive2lanelet/io/gui.py
opendrive2tessng/opendrive2lanelet/io/opendrive_convert.py
opendrive2tessng/opendrive2lanelet/io/osm_convert.py
opendrive2tessng/opendrive2lanelet/io/viewer.py
opendrive2tessng/opendrive2lanelet/io/visualize_commonroad.py
opendrive2tessng/opendrive2lanelet/opendriveparser/__init__.py
opendrive2tessng/opendrive2lanelet/opendriveparser/parser.py
opendrive2tessng/opendrive2lanelet/opendriveparser/elements/__init__.py
opendrive2tessng/opendrive2lanelet/opendriveparser/elements/eulerspiral.py
opendrive2tessng/opendrive2lanelet/opendriveparser/elements/geometry.py
opendrive2tessng/opendrive2lanelet/opendriveparser/elements/junction.py
opendrive2tessng/opendrive2lanelet/opendriveparser/elements/opendrive.py
opendrive2tessng/opendrive2lanelet/opendriveparser/elements/road.py
opendrive2tessng/opendrive2lanelet/opendriveparser/elements/roadElevationProfile.py
opendrive2tessng/opendrive2lanelet/opendriveparser/elements/roadLanes.py
opendrive2tessng/opendrive2lanelet/opendriveparser/elements/roadLateralProfile.py
opendrive2tessng/opendrive2lanelet/opendriveparser/elements/roadLink.py
opendrive2tessng/opendrive2lanelet/opendriveparser/elements/roadPlanView.py
opendrive2tessng/opendrive2lanelet/opendriveparser/elements/road_record.py
opendrive2tessng/opendrive2lanelet/opendriveparser/elements/roadtype.py
opendrive2tessng/opendrive2lanelet/osm/__init__.py
opendrive2tessng/opendrive2lanelet/osm/lanelet2osm.py
opendrive2tessng/opendrive2lanelet/osm/osm.py
opendrive2tessng/opendrive2lanelet/osm/osm2lanelet.py
opendrive2tessng-0.1.6.dist-info/LICENSE
opendrive2tessng-0.1.6.dist-info/METADATA
opendrive2tessng-0.1.6.dist-info/WHEEL
opendrive2tessng-0.1.6.dist-info/top_level.txt
opendrive2tessng-0.1.6.dist-info/RECORD
