Metadata-Version: 2.1
Name: opendrive2tessng
Version: 0.1.6
Summary: convert opendrive to road_network
Home-page: UNKNOWN
Author: Author
Author-email: 17315487709@163.com
License: UNKNOWN
Platform: UNKNOWN
Classifier: Programming Language :: Python :: 3
Classifier: License :: OSI Approved :: MIT License
Classifier: Operating System :: OS Independent
Requires-Python: >=3.6, <=3.8
License-File: LICENSE
Requires-Dist: matplotlib
Requires-Dist: lxml (>=4.9.1)
Requires-Dist: matlab (>=0.1)
Requires-Dist: numpy (>=1.19.5)
Requires-Dist: scipy (>=1.5.4)
Requires-Dist: commonroad.io (==2020.2)
